Metadata-Version: 2.1
Name: MirSerializer
Version: 1.0.2
Summary: Library for serialization JSON, XML
Home-page: UNKNOWN
Author: Mirolyubov Ilya
Author-email: ilyamir1@mail.ru
License: UNKNOWN
Platform: UNKNOWN
